Metadata-Version: 1.1
Name: thumbor-aliases
Version: 0.0.3
Summary: Thumbor URL Aliases
Home-page: http://github.com/dgarana/thumbor-aliases
Author: David Garaña
Author-email: UNKNOWN
License: MIT
Platform: any
Classifier: Intended Audience :: Developers
Classifier: License :: OSI Approved :: MIT License
Classifier: Operating System :: OS Independent
Classifier: Programming Language :: Python
Classifier: Topic :: Software Development :: Libraries :: Python Modules
